{"name":"Workshop Telefonia e Automacao","tagline":"Workshop de Telefonia e Automacão com Arduino e Asterisk.","body":"### Seja bem vindo ao Workshop de Telefonia e Automação com Asterisk, abrangendo Asterisk\r\nEste workshop tem como objetivo compartilhar e gerar conhecimento no uso do Arduino para automação e processamento de dados usando linhas telefônicas fixas, celular e PBXs Virtuais como o Asterisk.\r\n### Autores, Patrocínio, Apoio e Contribuições\r\nProfessor e Mediador @CarlosDelfino\r\nPatrocínio: Space4Me (http://www.space4me.com.br)\r\n\r\n### Suporte ou Contato\r\nMaiores informações podem ser solicitados no e-mail consultoria@carlosdelfino.eti.br ou pela página: http://www.carlosdelfino.eti.br ou mesmo pelo menu Issues deste projeto.\r\n\r\n\r\n","google":"UA-21710445-1","note":"Don't delete this file! It's used internally to help with page regeneration."}